openhub_django/__init__.py
openhub_django/affiliated_committers.py
openhub_django/apps.py
openhub_django/checker.py
openhub_django/data.py
openhub_django/models.py
openhub_django/organization.py
openhub_django/outside_committers.py
openhub_django/outside_projects.py
openhub_django/portfolio_projects.py
openhub_django/urls.py
openhub_django/variables.py
openhub_django/views.py
openhub_django/management/commands/import_affiliated_committers_data.py
openhub_django/management/commands/import_openhub_data.py
openhub_django/management/commands/import_organization_data.py
openhub_django/management/commands/import_outside_committers_data.py
openhub_django/management/commands/import_outside_projects_data.py
openhub_django/management/commands/import_portfolio_projects_data.py
openhub_django/migrations/0001_initial.py
openhub_django/migrations/__init__.py
openhub_django/static/css/openhub_django.css
openhub_django/static/js/openhub_django.js
openhub_django/templates/base.html
openhub_django/templates/openhub_django/affiliatedcommitter_detail.html
openhub_django/templates/openhub_django/affiliatedcommitter_list.html
openhub_django/templates/openhub_django/index.html
openhub_django/templates/openhub_django/organization_detail.html
openhub_django/templates/openhub_django/organization_list.html
openhub_django/templates/openhub_django/outsidecommitter_detail.html
openhub_django/templates/openhub_django/outsidecommitter_list.html
openhub_django/templates/openhub_django/outsideproject_detail.html
openhub_django/templates/openhub_django/outsideproject_list.html
openhub_django/templates/openhub_django/portfolioproject_detail.html
openhub_django/templates/openhub_django/portfolioproject_list.html
openhub_django-0.1.0.dist-info/AUTHORS.rst
openhub_django-0.1.0.dist-info/LICENSE
openhub_django-0.1.0.dist-info/METADATA
openhub_django-0.1.0.dist-info/WHEEL
openhub_django-0.1.0.dist-info/top_level.txt
openhub_django-0.1.0.dist-info/RECORD
