Metadata-Version: 2.1
Name: openhub-django
Version: 0.1.0
Summary: Integrate openhub APIs with Django
Home-page: https://github.com/sks444/openhub-django
Author: Shrikrishna Singh
Author-email: krishnasingh.ss30@gmail.com
License: MIT
Keywords: openhub-django
Platform: UNKNOWN
Classifier: Development Status :: 3 - Alpha
Classifier: Framework :: Django :: 1.11
Classifier: Intended Audience :: Developers
Classifier: License :: OSI Approved :: BSD License
Classifier: Natural Language :: English
Classifier: Programming Language :: Python :: 2
Classifier: Programming Language :: Python :: 2.7
Classifier: Programming Language :: Python :: 3
Classifier: Programming Language :: Python :: 3.4
Classifier: Programming Language :: Python :: 3.5
Classifier: Programming Language :: Python :: 3.6
Requires-Dist: django-model-utils (>=2.0)
Requires-Dist: xmltodict
Requires-Dist: python-decouple
Requires-Dist: django-distill
